{
  "english_content": {
    "categories": ["Single-player", "Steam Achievements", "Steam Cloud"],
    "genres": ["Free To Play"],
    "short_description": "Bitburner is a programming-based incremental game. Write scripts in JavaScript to automate gameplay, learn skills, play minigames, solve puzzles, and more in this cyberpunk text-based incremental RPG."
  },
  "german_content": {
    "categories": ["Einzelspieler", "Steam-Errungenschaften", "Steam Cloud"],
    "genres": ["Kostenlos spielbar"],
    "short_description": "Bitburner is a programming-based incremental game. Write scripts in JavaScript to automate gameplay, learn skills, play minigames, solve puzzles, and more in this cyberpunk text-based incremental RPG."
  },
  "image": "./bitburner.jpg",
  "is_free": true,
  "name": "Bitburner",
  "platforms": {
    "linux": true,
    "mac": true,
    "windows": true
  },
  "release_date": {
    "coming_soon": false,
    "date": "Dec 10, 2021"
  },
  "slug": "bitburner",
  "steamID": 1812820,
  "website": "https://bitburner-official.github.io/"
}
