{
    "archive": false,
    "description": "Increase Cycle Time ist Euer JobRad® Podcast für Software-Entwicklung. Und alles, was damit zusammenhängt.",
    "episodeCount": 7,
    "image": "./increase-cycle-time.png",
    "itunesID": 1825842432,
    "latestEpisodePublished": 1765350123,
    "name": "Increase Cycle Time - Der JobRad® Development Podcast",
    "podcastIndexID": 7407605,
    "rssFeed": "https://jobrad-increase-cycle-time.podigee.io/feed/mp3",
    "slug": "increase-cycle-time-der-jobrad-r-development-podcast",
    "spotify": "https://open.spotify.com/show/0hJlS2NMC0NEreoUzz7tp3?si=997aa47bd99b4ae3",
    "tags": [
        "Softwareentwicklung",
        "UX",
        "Produkt-Entwicklung",
        "Fahrrad",
        "Cycle Time"
    ],
    "website": "https://jobrad-increase-cycle-time.podigee.io/",
    "weekly_downloads_avg": {
        "updated": "2025-08-11",
        "value": 158
    }
}